{"chunk_definitions":[{"row":53,"row_count":1,"visible":true,"expansion_state":0,"options":{"engine":"r","label":"unnamed-chunk-9","dev":"png"},"document_id":"8FD8B626","chunk_id":"c2teoes6qk5rh","chunk_label":"unnamed-chunk-2"},{"row":105,"row_count":1,"visible":true,"expansion_state":0,"options":{"engine":"r","label":"unnamed-chunk-67","dev":"png"},"document_id":"8FD8B626","chunk_id":"czh7bc5l9isbg","chunk_label":"unnamed-chunk-3"},{"row":142,"row_count":1,"visible":true,"expansion_state":0,"options":{"engine":"r","label":"unnamed-chunk-68","dev":"png"},"document_id":"8FD8B626","chunk_id":"cbd1uxkn1gy7k","chunk_label":"unnamed-chunk-4"},{"row":170,"row_count":1,"visible":true,"expansion_state":0,"options":{"engine":"r","label":"unnamed-chunk-69","dev":"png"},"document_id":"8FD8B626","chunk_id":"c5kaygh3riesu","chunk_label":"unnamed-chunk-5"},{"row":211,"row_count":1,"visible":true,"expansion_state":0,"options":{"engine":"r","label":"unnamed-chunk-70","dev":"png"},"document_id":"8FD8B626","chunk_id":"c81dfohgkjjrd","chunk_label":"unnamed-chunk-6"},{"row":310,"row_count":1,"visible":true,"expansion_state":0,"options":{"engine":"r","label":"unnamed-chunk-71","dev":"png"},"document_id":"8FD8B626","chunk_id":"c8na8jd2e0ben","chunk_label":"unnamed-chunk-7"},{"row":340,"row_count":1,"visible":true,"expansion_state":0,"options":{"engine":"r","label":"unnamed-chunk-72","dev":"png"},"document_id":"8FD8B626","chunk_id":"c77immkee18ej","chunk_label":"unnamed-chunk-8"},{"row":392,"row_count":1,"visible":true,"expansion_state":0,"options":{"engine":"r","label":"unnamed-chunk-73","dev":"png"},"document_id":"8FD8B626","chunk_id":"cz3ht626bc5st","chunk_label":"unnamed-chunk-9"},{"row":469,"row_count":1,"visible":true,"expansion_state":0,"options":{"engine":"r","label":"unnamed-chunk-74","dev":"png"},"document_id":"8FD8B626","chunk_id":"cgu0k04bede3x","chunk_label":"unnamed-chunk-10"}],"doc_write_time":1744308586}